__init__.py
dict2obj.py
http.py
iplocation.py
mongo.py
setup.py
tyraellib.egg-info/PKG-INFO
tyraellib.egg-info/SOURCES.txt
tyraellib.egg-info/dependency_links.txt
tyraellib.egg-info/top_level.txt
tyraellib.egg-info/zip-safe