Metadata-Version: 1.1
Name: tyraellib
Version: 0.5.0
Summary: useful lib created by tyrael lau
Home-page: https://github.com/luke0922/tyraellib
Author: Tyrael Lau
Author-email: liqianglau@outlook.com
License: APLv2
Platform: any
Classifier: Programming Language :: Python :: 2.7
Classifier: Topic :: Internet :: WWW/HTTP :: Dynamic Content
Classifier: Topic :: Software Development :: Libraries :: Python Modules
